.cvsignore
EXTERNALS.txt
buildout.cfg
paste.cfg
setup.py
bootstrap/bootstrap.py
z3c/__init__.py
z3c.gibberish.egg-info/PKG-INFO
z3c.gibberish.egg-info/SOURCES.txt
z3c.gibberish.egg-info/dependency_links.txt
z3c.gibberish.egg-info/entry_points.txt
z3c.gibberish.egg-info/namespace_packages.txt
z3c.gibberish.egg-info/not-zip-safe
z3c.gibberish.egg-info/requires.txt
z3c.gibberish.egg-info/top_level.txt
z3c/gibberish/README.txt
z3c/gibberish/__init__.py
z3c/gibberish/tests.py
