Metadata-Version: 1.0
Name: z3c.gibberish
Version: 0.1
Summary: Generate CSV files containing random words from a dictionary
Home-page: http://cheeseshop.python.org/pypi/z3c.gibberish
Author: Ross Patterson
Author-email: me@rpatterson.net
License: GPL
Platform: UNKNOWN
Classifier: Framework :: Plone
Classifier: Framework :: Zope2
Classifier: Framework :: Zope3
Classifier: Programming Language :: Python
Classifier: Topic :: Software Development :: Libraries :: Python Modules
